{"cameraMode":{"drawMode":0,"name":"Shaded","section":"Shading Mode"},"sceneLighting":false,"audioPlay":false,"sceneViewState":{"m_AlwaysRefresh":false,"showFog":true,"showSkybox":false,"showFlares":true,"showImageEffects":true,"showParticleSystems":true,"showVisualEffectGraphs":true,"m_FxEnabled":true},"in2DMode":false,"pivot":{"x":-6.250263214111328,"y":4.269245624542236,"z":1.2764339447021485},"rotation":{"x":0.20470018684864045,"y":-0.04696356877684593,"z":0.009832433424890042,"w":0.9776512980461121},"size":8.81997013092041,"orthographic":false}