{"cameraMode":{"drawMode":0,"name":"Shaded","section":"Shading Mode"},"sceneLighting":false,"audioPlay":false,"sceneViewState":{"m_AlwaysRefresh":false,"showFog":true,"showSkybox":false,"showFlares":true,"showImageEffects":true,"showParticleSystems":true,"showVisualEffectGraphs":true,"m_FxEnabled":true},"in2DMode":false,"pivot":{"x":-3.429999828338623,"y":0.8327475190162659,"z":-2.3839120864868166},"rotation":{"x":-0.03180301561951637,"y":0.008092870935797692,"z":-0.00025757652474567294,"w":-0.9994621872901917},"size":1.1875030994415284,"orthographic":false}